qute_prueba_funciones/Funciones.py
qute_prueba_funciones/__init__.py
qute_prueba_funciones-0.0.1.dist-info/METADATA
qute_prueba_funciones-0.0.1.dist-info/WHEEL
qute_prueba_funciones-0.0.1.dist-info/top_level.txt
qute_prueba_funciones-0.0.1.dist-info/RECORD
